Metadata-Version: 2.1
Name: rsqlite-sync
Version: 0.0.3
Summary: Использование SQLite3 в многопоточных программах.
Home-page: UNKNOWN
Author-email: rapmbd@gmail.com
License: UNKNOWN
Platform: UNKNOWN
